{
    "props": [
        {
            "bathrooms": 6,
            "carouselPhotos": [
                {
                    "url": "https://photos.zillowstatic.com/fp/9df7d14060442e86b0da56e802cad34b-p_e.jpg"
                },
                {
                    "url": "https://photos.zillowstatic.com/fp/dcf5680f950e202a5c2853ec66a0350b-p_e.jpg"
                },
                {
                    "url": "https://photos.zillowstatic.com/fp/88af846fe7b7ba98b86b310c0cc64976-p_e.jpg"
                },
                {
                    "url": "https://photos.zillowstatic.com/fp/3e4f29364f27fe03940c0dac32fb9dce-p_e.jpg"
                },
                {
                    "url": "https://photos.zillowstatic.com/fp/779c5a73e9c6291018498c105371c48d-p_e.jpg"
                },
                {
                    "url": "https://photos.zillowstatic.com/fp/655b611434f83a27934ec7970f9b62da-p_e.jpg"
                },
                {
                    "url": "https://photos.zillowstatic.com/fp/cb6c9230d58f3c901b1a4bba35b617f1-p_e.jpg"
                },
                {
                    "url": "https://photos.zillowstatic.com/fp/be3a04567b474851e4cd15f84535fc41-p_e.jpg"
                },
                {
                    "url": "https://photos.zillowstatic.com/fp/7d1f81c43b7b92ac9ccce7771616e81c-p_e.jpg"
                },
                {
                    "url": "https://photos.zillowstatic.com/fp/73fab74dc8384ab34ca440bc1eea8944-p_e.jpg"
                },
                {
                    "url": "https://photos.zillowstatic.com/fp/cff2b4c6f4c1adc1f209eb0185d53e5b-p_e.jpg"
                },
                {
                    "url": "https://photos.zillowstatic.com/fp/0a25e215ef70448a826b8102d7b4d078-p_e.jpg"
                },
                {
                    "url": "https://photos.zillowstatic.com/fp/6f870d20f7f38a0c74c271247f224756-p_e.jpg"
                },
                {
                    "url": "https://photos.zillowstatic.com/fp/5a187a9c80ce4e484aac5134fd5d4db1-p_e.jpg"
                },
                {
                    "url": "https://photos.zillowstatic.com/fp/58a7111059922730c0f531dd747f6f7f-p_e.jpg"
                },
                {
                    "url": "https://photos.zillowstatic.com/fp/37e3ba2fe649b8863971b0d0a3a915ad-p_e.jpg"
                },
                {
                    "url": "https://photos.zillowstatic.com/fp/731337d84226564d3d997d88b0a5d9e6-p_e.jpg"
                },
                {
                    "url": "https://photos.zillowstatic.com/fp/660d51315c773bcb27ed65e3f0fa8d0f-p_e.jpg"
                },
                {
                    "url": "https://photos.zillowstatic.com/fp/872f07f1279a87ab9e411a8d0b9c5913-p_e.jpg"
                },
                {
                    "url": "https://photos.zillowstatic.com/fp/9b05b1969424535c087b31cf6b5aebd9-p_e.jpg"
                },
                {
                    "url": "https://photos.zillowstatic.com/fp/9074c6b3dafd35dfbfbc02ce7e1d5a7d-p_e.jpg"
                },
                {
                    "url": "https://photos.zillowstatic.com/fp/9f8f95d8d559a09fba55e288d2b00834-p_e.jpg"
                },
                {
                    "url": "https://photos.zillowstatic.com/fp/810c9759345733ee9f6fa3335b164c08-p_e.jpg"
                },
                {
                    "url": "https://photos.zillowstatic.com/fp/74a396813d5667fa2b65e721c2f2551f-p_e.jpg"
                },
                {
                    "url": "https://photos.zillowstatic.com/fp/55380bb3ad0279022c3cb4ccd425eb61-p_e.jpg"
                },
                {
                    "url": "https://photos.zillowstatic.com/fp/106cf5f6d2d78b9cd755b943e44af2b4-p_e.jpg"
                },
                {
                    "url": "https://photos.zillowstatic.com/fp/faa82543b9966033f36f4a2b9c347ee4-p_e.jpg"
                },
                {
                    "url": "https://photos.zillowstatic.com/fp/5fe5c6b2e3ec19e0408fe40d0b06ebf5-p_e.jpg"
                },
                {
                    "url": "https://photos.zillowstatic.com/fp/601ca4e24549fec23347df11b84f2963-p_e.jpg"
                },
                {
                    "url": "https://photos.zillowstatic.com/fp/086f99ee72a75e9fa8d9e555f89c542b-p_e.jpg"
                },
                {
                    "url": "https://photos.zillowstatic.com/fp/acc416c5bb580bf3368d1789340211e9-p_e.jpg"
                },
                {
                    "url": "https://photos.zillowstatic.com/fp/b6118653297c74ece04d9b0d1d0ed53e-p_e.jpg"
                }
            ],
            "has3DModel": false,
            "propertyType": "TOWNHOUSE",
            "longitude": -73.96042,
            "livingArea": 7910,
            "address": "161 E 74th St, New York, NY 10021",
            "rentZestimate": 44504,
            "variableData": null,
            "priceChange": -390000,
            "zestimate": 9055600,
            "imgSrc": "https://photos.zillowstatic.com/fp/9df7d14060442e86b0da56e802cad34b-p_e.jpg",
            "latitude": 40.77164,
            "price": 9500000,
            "bedrooms": 7,
            "lotAreaValue": null,
            "hasVideo": false,
            "lotAreaUnit": null,
            "listingStatus": "FOR_SALE",
            "zpid": "31535465",
            "listingSubType": {
                "is_FSBA": true
            },
            "detailUrl": "/homedetails/161-E-74th-St-New-York-NY-10021/31535465_zpid/",
            "contingentListingType": null,
            "daysOnZillow": 62,
            "datePriceChanged": 1736409600000,
            "country": "USA",
            "currency": "USD",
            "comingSoonOnMarketDate": null,
            "hasImage": true
        },
        {
            "bathrooms": 7,
            "carouselPhotos": [
                {
                    "url": "https://photos.zillowstatic.com/fp/18744ad707e466224b6a071112b74528-p_e.jpg"
                },
                {
                    "url": "https://photos.zillowstatic.com/fp/9a51ad2238293574e2ae74950466adce-p_e.jpg"
                },
                {
                    "url": "https://photos.zillowstatic.com/fp/7e253cd5b29e52d8c448d228d201a854-p_e.jpg"
                },
                {
                    "url": "https://photos.zillowstatic.com/fp/d7546ca3ce0e106d93a6a6e2e0c89427-p_e.jpg"
                },
                {
                    "url": "https://photos.zillowstatic.com/fp/c4f6bf8b7186da3e97586931826b2c04-p_e.jpg"
                },
                {
                    "url": "https://photos.zillowstatic.com/fp/d37209e18ce0bc017cf7ce1584790942-p_e.jpg"
                },
                {
                    "url": "https://photos.zillowstatic.com/fp/36f3f6735678b26131a9122fc775b96e-p_e.jpg"
                },
                {
                    "url": "https://photos.zillowstatic.com/fp/af15687383bf98fae7b3255eaaa2ff86-p_e.jpg"
                },
                {
                    "url": "https://photos.zillowstatic.com/fp/3a3836a6fdcd03c20b72bf99852531b1-p_e.jpg"
                },
                {
                    "url": "https://photos.zillowstatic.com/fp/5fdb3454058ccce769800cdf0f8603bf-p_e.jpg"
                },
                {
                    "url": "https://photos.zillowstatic.com/fp/b70f3a97984fd3278abb6443c02310ad-p_e.jpg"
                },
                {
                    "url": "https://photos.zillowstatic.com/fp/fde72b97ded6796b6fec4fb56db178b4-p_e.jpg"
                },
                {
                    "url": "https://photos.zillowstatic.com/fp/eabdcc6834c182ed2bd85a5fec842818-p_e.jpg"
                },
                {
                    "url": "https://photos.zillowstatic.com/fp/b888a64e2f2f8b46f9518c02c325edf4-p_e.jpg"
                },
                {
                    "url": "https://photos.zillowstatic.com/fp/1505bbc31b9e2b31c3208a38d32b8779-p_e.jpg"
                },
                {
                    "url": "https://photos.zillowstatic.com/fp/a3dfc72d55a140cae55bc7ab0e919d5d-p_e.jpg"
                },
                {
                    "url": "https://photos.zillowstatic.com/fp/2a900fa9717d5693d41186c9f9f38385-p_e.jpg"
                },
                {
                    "url": "https://photos.zillowstatic.com/fp/3c56a56d415e28236076955f19eb5efa-p_e.jpg"
                },
                {
                    "url": "https://photos.zillowstatic.com/fp/3b16f4ab96e1f67fc5fd705522fa4655-p_e.jpg"
                },
                {
                    "url": "https://photos.zillowstatic.com/fp/d3fabf86dfc4a95d43013be9781db2fa-p_e.jpg"
                },
                {
                    "url": "https://photos.zillowstatic.com/fp/53e4bce9e4f8a9f64a51a034b71da7f2-p_e.jpg"
                },
                {
                    "url": "https://photos.zillowstatic.com/fp/2059c2dd3795de1aa345bcad17098959-p_e.jpg"
                },
                {
                    "url": "https://photos.zillowstatic.com/fp/821fefcb8b1b2d57a15bd738b4b35a09-p_e.jpg"
                },
                {
                    "url": "https://photos.zillowstatic.com/fp/5d5817fc2de2cd6e4a1bd650124d3f82-p_e.jpg"
                }
            ],
            "has3DModel": false,
            "propertyType": "SINGLE_FAMILY",
            "longitude": -73.96027,
            "livingArea": 6700,
            "address": "180 E 75th St, New York, NY 10021",
            "rentZestimate": 6124,
            "variableData": null,
            "priceChange": null,
            "zestimate": 11801500,
            "imgSrc": "https://photos.zillowstatic.com/fp/18744ad707e466224b6a071112b74528-p_e.jpg",
            "latitude": 40.771908,
            "price": 12495000,
            "bedrooms": 6,
            "lotAreaValue": null,
            "hasVideo": false,
            "lotAreaUnit": null,
            "listingStatus": "FOR_SALE",
            "zpid": "31535486",
            "listingSubType": {
                "is_FSBA": true
            },
            "detailUrl": "/homedetails/180-E-75th-St-New-York-NY-10021/31535486_zpid/",
            "contingentListingType": null,
            "daysOnZillow": 55,
            "datePriceChanged": null,
            "country": "USA",
            "currency": "USD",
            "comingSoonOnMarketDate": null,
            "hasImage": true
        },
        {
            "bathrooms": 5,
            "carouselPhotos": [
                {
                    "url": "https://photos.zillowstatic.com/fp/1bd4ce58220c082367e9437eeef89419-p_e.jpg"
                },
                {
                    "url": "https://photos.zillowstatic.com/fp/e7ec685f8a25a8544a4024c9e15ff95f-p_e.jpg"
                },
                {
                    "url": "https://photos.zillowstatic.com/fp/865d6de52d216daa04e534fb83d2ff0a-p_e.jpg"
                },
                {
                    "url": "https://photos.zillowstatic.com/fp/daf1602984e11d79cdde54bff370a1d2-p_e.jpg"
                },
                {
                    "url": "https://photos.zillowstatic.com/fp/47e5b6056d538169464d978cfeb796dd-p_e.jpg"
                },
                {
                    "url": "https://photos.zillowstatic.com/fp/c6a05b475137ce2a503e1d09fdef3bd7-p_e.jpg"
                },
                {
                    "url": "https://photos.zillowstatic.com/fp/76899bfc3696dd23fbe466510b2b2e8f-p_e.jpg"
                },
                {
                    "url": "https://photos.zillowstatic.com/fp/f4adc8c9e49b3cfdd43ad77f744e72d5-p_e.jpg"
                },
                {
                    "url": "https://photos.zillowstatic.com/fp/3f5a54d025150e17a78a41e6b89b5cd0-p_e.jpg"
                },
                {
                    "url": "https://photos.zillowstatic.com/fp/e1bc430cd9a92a7f8b59d0ae8ca6e461-p_e.jpg"
                },
                {
                    "url": "https://photos.zillowstatic.com/fp/688b4237fd04340cc36e795121a31473-p_e.jpg"
                },
                {
                    "url": "https://photos.zillowstatic.com/fp/3044f03c7209ea714a0deb86fe46f1c2-p_e.jpg"
                },
                {
                    "url": "https://photos.zillowstatic.com/fp/963da89969c1f03020b50253e2f37f6c-p_e.jpg"
                },
                {
                    "url": "https://photos.zillowstatic.com/fp/1ea0d0b653911bf55d75f56a272f9d13-p_e.jpg"
                },
                {
                    "url": "https://photos.zillowstatic.com/fp/8c20cbdbc375c6f2007df20a8c3c40bf-p_e.jpg"
                },
                {
                    "url": "https://photos.zillowstatic.com/fp/15ecb83282c17cffc9b60f851edc0caa-p_e.jpg"
                },
                {
                    "url": "https://photos.zillowstatic.com/fp/3dac15e2cdd49d628b42545776a936ca-p_e.jpg"
                },
                {
                    "url": "https://photos.zillowstatic.com/fp/5fdbd00f5be37aeb84c9b2b6021a0729-p_e.jpg"
                },
                {
                    "url": "https://photos.zillowstatic.com/fp/c580ebc434d501f01cee1323cc5e58a9-p_e.jpg"
                },
                {
                    "url": "https://photos.zillowstatic.com/fp/f6906e4cf90fc55e4d14907760987d9f-p_e.jpg"
                },
                {
                    "url": "https://photos.zillowstatic.com/fp/d9ef21058937b70c8d38c952c45f441a-p_e.jpg"
                },
                {
                    "url": "https://photos.zillowstatic.com/fp/7af2b5816f7e2ae512760beeba1948ee-p_e.jpg"
                },
                {
                    "url": "https://photos.zillowstatic.com/fp/414c309c6353585e774130f4b577ba3e-p_e.jpg"
                },
                {
                    "url": "https://photos.zillowstatic.com/fp/b09a067fc8aa61b7ef9e04157124e4db-p_e.jpg"
                },
                {
                    "url": "https://photos.zillowstatic.com/fp/ef99d50ed6932ed1e4784d38b393a0b4-p_e.jpg"
                },
                {
                    "url": "https://photos.zillowstatic.com/fp/9395c3b6895da0e2cc1d22d182b67d16-p_e.jpg"
                },
                {
                    "url": "https://photos.zillowstatic.com/fp/a29d39787fbc53e5aa378e2f388544b2-p_e.jpg"
                },
                {
                    "url": "https://photos.zillowstatic.com/fp/1b99e2acceaa8da03356d0c38f82a11c-p_e.jpg"
                }
            ],
            "has3DModel": false,
            "propertyType": "TOWNHOUSE",
            "longitude": -73.959,
            "livingArea": 0,
            "address": "328 E 69th St, New York, NY 10021",
            "rentZestimate": 8174,
            "variableData": null,
            "priceChange": null,
            "zestimate": 6507100,
            "imgSrc": "https://photos.zillowstatic.com/fp/1bd4ce58220c082367e9437eeef89419-p_e.jpg",
            "latitude": 40.766327,
            "price": 6495000,
            "bedrooms": 4,
            "lotAreaValue": null,
            "hasVideo": false,
            "lotAreaUnit": null,
            "listingStatus": "FOR_SALE",
            "zpid": "31538118",
            "listingSubType": {
                "is_FSBA": true
            },
            "detailUrl": "/homedetails/328-E-69th-St-New-York-NY-10021/31538118_zpid/",
            "contingentListingType": null,
            "daysOnZillow": 56,
            "datePriceChanged": null,
            "country": "USA",
            "currency": "USD",
            "comingSoonOnMarketDate": null,
            "hasImage": true
        },
        {
            "bathrooms": 8,
            "carouselPhotos": [
                {
                    "url": "https://photos.zillowstatic.com/fp/8c3ca8c14bbfa9249adc5f51482f74fe-p_e.jpg"
                },
                {
                    "url": "https://photos.zillowstatic.com/fp/0df7b5144be3b447e670e00ee7463e33-p_e.jpg"
                },
                {
                    "url": "https://photos.zillowstatic.com/fp/63d0d237815adabdc5aa09abb7d076da-p_e.jpg"
                },
                {
                    "url": "https://photos.zillowstatic.com/fp/f06c031af1d8ada5198e419e9a22777f-p_e.jpg"
                },
                {
                    "url": "https://photos.zillowstatic.com/fp/c6f03623b2a64b1b65d1ca48927a6750-p_e.jpg"
                },
                {
                    "url": "https://photos.zillowstatic.com/fp/3552c4ef026dfb3115f54b1c7b1a71f8-p_e.jpg"
                },
                {
                    "url": "https://photos.zillowstatic.com/fp/2f47e1e3a657358d9412cef94e4f14a3-p_e.jpg"
                },
                {
                    "url": "https://photos.zillowstatic.com/fp/27877eecc89ae21ec7eec3d58393acc2-p_e.jpg"
                },
                {
                    "url": "https://photos.zillowstatic.com/fp/e4e701e13b822791f12b6914f746750b-p_e.jpg"
                },
                {
                    "url": "https://photos.zillowstatic.com/fp/4ea18c534d6bb5e6a1525239291e975e-p_e.jpg"
                },
                {
                    "url": "https://photos.zillowstatic.com/fp/6afcc5e3b88009f4c76381c48b6b35e9-p_e.jpg"
                },
                {
                    "url": "https://photos.zillowstatic.com/fp/45431a034cbaa05f06d10ac89913d72f-p_e.jpg"
                },
                {
                    "url": "https://photos.zillowstatic.com/fp/5981e32f40864a6c6f912412870945df-p_e.jpg"
                },
                {
                    "url": "https://photos.zillowstatic.com/fp/7f4b5221f6436efbe75b81103a3e8fd1-p_e.jpg"
                },
                {
                    "url": "https://photos.zillowstatic.com/fp/d7b359ead1ccbb32cc66c129463f4003-p_e.jpg"
                }
            ],
            "has3DModel": false,
            "propertyType": "TOWNHOUSE",
            "longitude": -73.967354,
            "livingArea": 8790,
            "address": "7 E 69th St, New York, NY 10021",
            "rentZestimate": 82856,
            "variableData": null,
            "priceChange": -550000,
            "zestimate": 11379700,
            "imgSrc": "https://photos.zillowstatic.com/fp/8c3ca8c14bbfa9249adc5f51482f74fe-p_e.jpg",
            "latitude": 40.77031,
            "price": 11950000,
            "bedrooms": 6,
            "lotAreaValue": null,
            "hasVideo": false,
            "lotAreaUnit": null,
            "listingStatus": "FOR_SALE",
            "zpid": "31533680",
            "listingSubType": {
                "is_FSBA": true
            },
            "detailUrl": "/homedetails/7-E-69th-St-New-York-NY-10021/31533680_zpid/",
            "contingentListingType": null,
            "daysOnZillow": 950,
            "datePriceChanged": 1733817600000,
            "country": "USA",
            "currency": "USD",
            "comingSoonOnMarketDate": null,
            "hasImage": true
        },
        {
            "bathrooms": 7,
            "carouselPhotos": [
                {
                    "url": "https://photos.zillowstatic.com/fp/5b9573ae1882ae1b7e1c72212dd93c19-p_e.jpg"
                },
                {
                    "url": "https://photos.zillowstatic.com/fp/9036df8a02e6558dd433f10f53989243-p_e.jpg"
                }
            ],
            "has3DModel": false,
            "propertyType": "TOWNHOUSE",
            "longitude": -73.96434,
            "livingArea": 7480,
            "address": "48 E 73rd St, New York, NY 10021",
            "rentZestimate": 50709,
            "variableData": null,
            "priceChange": -300001,
            "zestimate": null,
            "imgSrc": "https://photos.zillowstatic.com/fp/5b9573ae1882ae1b7e1c72212dd93c19-p_e.jpg",
            "latitude": 40.77196,
            "price": 7499999,
            "bedrooms": 8,
            "lotAreaValue": null,
            "hasVideo": false,
            "lotAreaUnit": null,
            "listingStatus": "FOR_SALE",
            "zpid": "31533816",
            "listingSubType": {
                "is_FSBA": true
            },
            "detailUrl": "/homedetails/48-E-73rd-St-New-York-NY-10021/31533816_zpid/",
            "contingentListingType": null,
            "daysOnZillow": 784,
            "datePriceChanged": 1736150400000,
            "country": "USA",
            "currency": "USD",
            "comingSoonOnMarketDate": null,
            "hasImage": true
        },
        {
            "bathrooms": 6,
            "carouselPhotos": [
                {
                    "url": "https://photos.zillowstatic.com/fp/056952abb696b16ae60d8aa11365b163-p_e.jpg"
                },
                {
                    "url": "https://photos.zillowstatic.com/fp/4ccb07ab3fa43ed64c50a10de79e380c-p_e.jpg"
                },
                {
                    "url": "https://photos.zillowstatic.com/fp/12d9ed32db7c83e2e0e9d647a846ccdc-p_e.jpg"
                },
                {
                    "url": "https://photos.zillowstatic.com/fp/1245c8818839a91d2fbb8083ed64f648-p_e.jpg"
                },
                {
                    "url": "https://photos.zillowstatic.com/fp/88220a5489615f8223f42a6cf964a314-p_e.jpg"
                },
                {
                    "url": "https://photos.zillowstatic.com/fp/41743ea51e93003b4e5fc7915a7da19f-p_e.jpg"
                },
                {
                    "url": "https://photos.zillowstatic.com/fp/714190b0c5589cdd66d70dcfc0370934-p_e.jpg"
                },
                {
                    "url": "https://photos.zillowstatic.com/fp/94808164d8c6ed159d5727b325121481-p_e.jpg"
                },
                {
                    "url": "https://photos.zillowstatic.com/fp/5a415beb57d3b33aab641a43e3809af4-p_e.jpg"
                },
                {
                    "url": "https://photos.zillowstatic.com/fp/d838180f2ddeb879a5b4efc6ca950448-p_e.jpg"
                },
                {
                    "url": "https://photos.zillowstatic.com/fp/3f71b0e4789d99ea74ca920847797595-p_e.jpg"
                },
                {
                    "url": "https://photos.zillowstatic.com/fp/ea30c1bcf563e04c8cb196a7d4599b64-p_e.jpg"
                },
                {
                    "url": "https://photos.zillowstatic.com/fp/9631a7ef09a86605cab63c57f0b10c8c-p_e.jpg"
                },
                {
                    "url": "https://photos.zillowstatic.com/fp/580887f64cb003feb89af29b530fd88d-p_e.jpg"
                }
            ],
            "has3DModel": false,
            "propertyType": "SINGLE_FAMILY",
            "longitude": -73.96214,
            "livingArea": 0,
            "address": "159 E 71st St, New York, NY 10021",
            "rentZestimate": 33879,
            "variableData": null,
            "priceChange": null,
            "zestimate": 8753800,
            "imgSrc": "https://photos.zillowstatic.com/fp/056952abb696b16ae60d8aa11365b163-p_e.jpg",
            "latitude": 40.769753,
            "price": 8700000,
            "bedrooms": 7,
            "lotAreaValue": null,
            "hasVideo": false,
            "lotAreaUnit": null,
            "listingStatus": "FOR_SALE",
            "zpid": "31535244",
            "listingSubType": {
                "is_FSBA": true
            },
            "detailUrl": "/homedetails/159-E-71st-St-New-York-NY-10021/31535244_zpid/",
            "contingentListingType": null,
            "daysOnZillow": 177,
            "datePriceChanged": null,
            "country": "USA",
            "currency": "USD",
            "comingSoonOnMarketDate": null,
            "hasImage": true
        },
        {
            "bathrooms": 6,
            "carouselPhotos": [
                {
                    "url": "https://photos.zillowstatic.com/fp/3c8642f13904182acdaf7019973569c0-p_e.jpg"
                },
                {
                    "url": "https://photos.zillowstatic.com/fp/7f810618b484c879a8094dca2e3435db-p_e.jpg"
                },
                {
                    "url": "https://photos.zillowstatic.com/fp/ad48299d575aa5f853ff9d30019b1735-p_e.jpg"
                },
                {
                    "url": "https://photos.zillowstatic.com/fp/855b37b4e1692811f342ff65659f7598-p_e.jpg"
                },
                {
                    "url": "https://photos.zillowstatic.com/fp/57ae7142fc09440e616440c2700f5a33-p_e.jpg"
                },
                {
                    "url": "https://photos.zillowstatic.com/fp/5071ad3d19fb29a764b8b2195e94009b-p_e.jpg"
                },
                {
                    "url": "https://photos.zillowstatic.com/fp/b894523a1289b0c79740c3b3e00f9e68-p_e.jpg"
                },
                {
                    "url": "https://photos.zillowstatic.com/fp/7f408c2518c0f184e932726aea1ae52c-p_e.jpg"
                },
                {
                    "url": "https://photos.zillowstatic.com/fp/9306ac8d07692b9a31706bd8d4517571-p_e.jpg"
                },
                {
                    "url": "https://photos.zillowstatic.com/fp/a35f6181e195291d8b1346d978bcf60d-p_e.jpg"
                },
                {
                    "url": "https://photos.zillowstatic.com/fp/161ace0076a5d1b5c5cf5eaed3c144f4-p_e.jpg"
                },
                {
                    "url": "https://photos.zillowstatic.com/fp/a3568b1baf1e09c9aafafa0c95a8aca7-p_e.jpg"
                },
                {
                    "url": "https://photos.zillowstatic.com/fp/45e717df985ee86d3d2eda2e2eb10650-p_e.jpg"
                },
                {
                    "url": "https://photos.zillowstatic.com/fp/585e12ee7a8af1c34a69ca0ec8026649-p_e.jpg"
                },
                {
                    "url": "https://photos.zillowstatic.com/fp/54ffffc438912854f67a7943ebb98758-p_e.jpg"
                },
                {
                    "url": "https://photos.zillowstatic.com/fp/a2d3fb7eb2df5e1d279f68be5170f370-p_e.jpg"
                },
                {
                    "url": "https://photos.zillowstatic.com/fp/199e78c599109887c55e2836b37291aa-p_e.jpg"
                },
                {
                    "url": "https://photos.zillowstatic.com/fp/0d89b768953857f8e656f47a1af2700a-p_e.jpg"
                },
                {
                    "url": "https://photos.zillowstatic.com/fp/2b2c02f3704e6df6e3140d04b8468a56-p_e.jpg"
                },
                {
                    "url": "https://photos.zillowstatic.com/fp/50a82738054ac71732b2c008e656c2f6-p_e.jpg"
                },
                {
                    "url": "https://photos.zillowstatic.com/fp/dd39f8b91cf3487a9c3da85155163db7-p_e.jpg"
                },
                {
                    "url": "https://photos.zillowstatic.com/fp/e8f3937e095a8bbfa39b4f32df5e9952-p_e.jpg"
                },
                {
                    "url": "https://photos.zillowstatic.com/fp/c6a9d3e6c69a6642d61b4cf8c7497d0a-p_e.jpg"
                },
                {
                    "url": "https://photos.zillowstatic.com/fp/34ccf28d706f165f471ebb37a18ac01d-p_e.jpg"
                }
            ],
            "has3DModel": false,
            "propertyType": "TOWNHOUSE",
            "longitude": -73.96097,
            "livingArea": 4800,
            "address": "152 E 74th St, New York, NY 10021",
            "rentZestimate": 7765,
            "variableData": null,
            "priceChange": -1000000,
            "zestimate": null,
            "imgSrc": "https://photos.zillowstatic.com/fp/3c8642f13904182acdaf7019973569c0-p_e.jpg",
            "latitude": 40.771427,
            "price": 11000000,
            "bedrooms": 5,
            "lotAreaValue": null,
            "hasVideo": false,
            "lotAreaUnit": null,
            "listingStatus": "FOR_SALE",
            "zpid": "65294358",
            "listingSubType": {
                "is_FSBA": true
            },
            "detailUrl": "/homedetails/152-E-74th-St-New-York-NY-10021/65294358_zpid/",
            "contingentListingType": null,
            "daysOnZillow": 775,
            "datePriceChanged": 1729926000000,
            "country": "USA",
            "currency": "USD",
            "comingSoonOnMarketDate": null,
            "hasImage": true
        }
    ],
    "resultsPerPage": 41,
    "totalPages": 1,
    "totalResultCount": 16,
    "schools": {},
    "currentPage": 1
}